gsp/__main__.py
gsp/tools.py
gsp-0.4.0.dist-info/LICENSE
gsp-0.4.0.dist-info/WHEEL
gsp-0.4.0.dist-info/METADATA
gsp-0.4.0.dist-info/RECORD
