Metadata-Version: 2.1
Name: gsp
Version: 0.4.0
Summary: Google Sheet Poster
License: GPL-3.0-or-later
Author: juke
Author-email: juke@free.fr
Requires-Python: >=3.9,<4.0
Classifier: License :: OSI Approved :: GNU General Public License v3 or later (GPLv3+)
Classifier: Programming Language :: Python :: 3
Classifier: Programming Language :: Python :: 3.10
Classifier: Programming Language :: Python :: 3.9
Requires-Dist: gspread (>=5.3.0,<6.0.0)
Requires-Dist: typer (>=0.4.0,<0.5.0)
